page_encryptor/__init__.py
page_encryptor/encryptor.py
page_encryptor/templates/decryptor_template.html
page_encryptor-0.6.1.dist-info/licenses/LICENSE
page_encryptor-0.6.1.dist-info/METADATA
page_encryptor-0.6.1.dist-info/WHEEL
page_encryptor-0.6.1.dist-info/entry_points.txt
page_encryptor-0.6.1.dist-info/top_level.txt
page_encryptor-0.6.1.dist-info/RECORD
