Metadata-Version: 2.4
Name: page-encryptor
Version: 0.6.1
Summary: Offline HTML encryption with in-browser decryption, inspired by PageCrypt
Author: Carlos Asmat
License: MIT
Project-URL: Homepage, https://gitlab.com/sotilrac/page-encryptor
Requires-Python: >=3.11
License-File: LICENSE
Requires-Dist: pycryptodome>=3.23.0
Provides-Extra: dev
Requires-Dist: black; extra == "dev"
Requires-Dist: pre-commit; extra == "dev"
Requires-Dist: ruff; extra == "dev"
Requires-Dist: pytest; extra == "dev"
Dynamic: license-file
